daisy/__init__.py
daisy/block.py
daisy/block_bookkeeper.py
daisy/blocks.py
daisy/cl_monitor.py
daisy/client.py
daisy/context.py
daisy/convenience.py
daisy/coordinate.py
daisy/dependency_graph.py
daisy/freezable.py
daisy/logging.py
daisy/processing_queue.py
daisy/ready_surface.py
daisy/roi.py
daisy/scheduler.py
daisy/serial_server.py
daisy/server.py
daisy/server_observer.py
daisy/task.py
daisy/task_state.py
daisy/task_worker_pools.py
daisy/worker.py
daisy/worker_pool.py
daisy/messages/__init__.py
daisy/messages/acquire_block.py
daisy/messages/block_failed.py
daisy/messages/client_exception.py
daisy/messages/exceptions.py
daisy/messages/message.py
daisy/messages/release_block.py
daisy/messages/request_shutdown.py
daisy/messages/send_block.py
daisy/tcp/__init__.py
daisy/tcp/exceptions.py
daisy/tcp/internal_messages.py
daisy/tcp/io_looper.py
daisy/tcp/tcp_client.py
daisy/tcp/tcp_message.py
daisy/tcp/tcp_server.py
daisy/tcp/tcp_stream.py
daisy-1.2.2.dist-info/LICENSE
daisy-1.2.2.dist-info/METADATA
daisy-1.2.2.dist-info/WHEEL
daisy-1.2.2.dist-info/top_level.txt
daisy-1.2.2.dist-info/RECORD
