Metadata-Version: 2.1
Name: daisy
Version: 1.2.2
Summary: Blockwise task scheduler for processing large volumetric data.
Author-email: William Patton <pattonw@hhmi.org>, Jan Funke <funkej@janelia.hhmi.org>, "Tri M. Nguyen" <tri_nguyen@hms.harvard.edu>, Caroline Malin-Mayor <malinmayorc@janelia.hhmi.org>
License: MIT
Classifier: Programming Language :: Python :: 3
Requires-Python: >=3.10
License-File: LICENSE
Requires-Dist: numpy
Requires-Dist: tornado>=5
Requires-Dist: tqdm
Requires-Dist: funlib.math
Requires-Dist: funlib.geometry
Requires-Dist: dill
Provides-Extra: dev
Requires-Dist: pytest; extra == "dev"
Requires-Dist: black; extra == "dev"
Requires-Dist: mypy; extra == "dev"
Requires-Dist: filelock; extra == "dev"
